{
  "actions": {
    "BankCardOCR": [
      {
        "document": "",
        "input": "https://ocr.tencentcloudapi.com/?Action=BankCardOCR\n&ImageUrl=https://xx/a.jpg\n&<Common request parameters>",
        "output": "{\r\n    \"Response\": {\r\n        \"BankInfo\": \"China Merchants Bank (03080000)\",\r\n        \"ValidDate\": \"07/2023\",\r\n        \"CardType\": \"Credit card\",\r\n        \"CardName\": \"China Merchants Bank credit card\",\r\n        \"BorderCutImage\": null,\r\n        \"CardNoImage\": null,\r\n        \"WarningCode\":  [\r\n            -9110\r\n        ], \r\n        \"CardNo\": \"6225768888888888\",\r\n        \"RequestId\": \"68f8fcbf-6004-0111a-ac18-6f1a9308fs100mab\"\r\n    }\r\n}",
        "title": "Recognizing a bank card"
      }
    ],
    "GeneralAccurateOCR": [
      {
        "document": "",
        "input": "https://ocr.tencentcloudapi.com/?Action=GeneralAccurateOCR\n&ImageUrl=https://xx/a.jpg\n&<Common request parameters>",
        "output": "{\r\n    \"Response\": {\r\n        \"TextDetections\": [\r\n            {\r\n                \"DetectedText\": \"Confetteria\",\r\n                \"Confidence\": 99,\r\n                \"ItemPolygon\": {\r\n                    \"X\": 449,\r\n                    \"Y\": 211,\r\n                    \"Width\": 115,\r\n                    \"Height\": 37\r\n                },\r\n                \"Polygon\": [\r\n                    {\r\n                        \"X\": 449,\r\n                        \"Y\": 231\r\n                    },\r\n                    {\r\n                        \"X\": 452,\r\n                        \"Y\": 211\r\n                    },\r\n                    {\r\n                        \"X\": 563,\r\n                        \"Y\": 227\r\n                    },\r\n                    {\r\n                        \"X\": 560,\r\n                        \"Y\": 247\r\n                    }\r\n                ],\r\n                \"AdvancedInfo\": \"{\\\"Parag\\\":{\\\"ParagNo\\\":1}}\"\r\n            },\r\n            {\r\n                \"DetectedText\": \"Raffaello\",\r\n                \"Confidence\": 99,\r\n                \"ItemPolygon\": {\r\n                    \"X\": 361,\r\n                    \"Y\": 242,\r\n                    \"Width\": 288,\r\n                    \"Height\": 97\r\n                },\r\n                \"Polygon\": [\r\n                    {\r\n                        \"X\": 361,\r\n                        \"Y\": 308\r\n                    },\r\n                    {\r\n                        \"X\": 368,\r\n                        \"Y\": 242\r\n                    },\r\n                    {\r\n                        \"X\": 648,\r\n                        \"Y\": 271\r\n                    },\r\n                    {\r\n                        \"X\": 641,\r\n                        \"Y\": 338\r\n                    }\r\n                ],\r\n                \"AdvancedInfo\": \"{\\\"Parag\\\":{\\\"ParagNo\\\":2}}\"\r\n            },\r\n            {\r\n                \"DetectedText\": \"Ferrero\",\r\n                \"Confidence\": 99,\r\n                \"ItemPolygon\": {\r\n                    \"X\": 394,\r\n                    \"Y\": 316,\r\n                    \"Width\": 200,\r\n                    \"Height\": 56\r\n                },\r\n                \"Polygon\": [\r\n                    {\r\n                        \"X\": 394,\r\n                        \"Y\": 349\r\n                    },\r\n                    {\r\n                        \"X\": 398,\r\n                        \"Y\": 316\r\n                    },\r\n                    {\r\n                        \"X\": 593,\r\n                        \"Y\": 337\r\n                    },\r\n                    {\r\n                        \"X\": 589,\r\n                        \"Y\": 371\r\n                    }\r\n                ],\r\n                \"AdvancedInfo\": \"{\\\"Parag\\\":{\\\"ParagNo\\\":2}}\"\r\n            },\r\n            {\r\n                \"DetectedText\": \"Raffaello@Confetteria\",\r\n                \"Confidence\": 98,\r\n                \"ItemPolygon\": {\r\n                    \"X\": 381,\r\n                    \"Y\": 368,\r\n                    \"Width\": 214,\r\n                    \"Height\": 55\r\n                },\r\n                \"Polygon\": [\r\n                    {\r\n                        \"X\": 381,\r\n                        \"Y\": 401\r\n                    },\r\n                    {\r\n                        \"X\": 385,\r\n                        \"Y\": 368\r\n                    },\r\n                    {\r\n                        \"X\": 594,\r\n                        \"Y\": 389\r\n                    },\r\n                    {\r\n                        \"X\": 590,\r\n                        \"Y\": 422\r\n                    }\r\n                ],\r\n                \"AdvancedInfo\": \"{\\\"Parag\\\":{\\\"ParagNo\\\":2}}\"\r\n            }\r\n        ],\r\n        \"Angel\": 0,\r\n        \"RequestId\": \"d2a1c039-817d-455b-b2e2-f765a7261906\"\r\n    }\r\n}",
        "title": "Recognizing general print (high-precision) ([debugging tool](https://console.cloud.tencent.com/api/explorer?Product=ocr&Action=GeneralAccurateOCR))"
      }
    ],
    "GeneralBasicOCR": [
      {
        "document": "",
        "input": "https://ocr.tencentcloudapi.com/?Action=GeneralBasicOCR\n&ImageUrl=https://xx/a.jpg\n&<Common request parameters>",
        "output": "{\r\n    \"Response\": {\r\n        \"TextDetections\": [\r\n            {\r\n                \"DetectedText\": \"Confetteria\",\r\n                \"Confidence\": 99,\r\n                \"ItemPolygon\": {\r\n                    \"X\": 473,\r\n                    \"Y\": 273,\r\n                    \"Width\": 112,\r\n                    \"Height\": 22\r\n                },\r\n                \"Polygon\": [\r\n                    {\r\n                        \"X\": 450,\r\n                        \"Y\": 211\r\n                    },\r\n                    {\r\n                        \"X\": 560,\r\n                        \"Y\": 223\r\n                    },\r\n                    {\r\n                        \"X\": 558,\r\n                        \"Y\": 244\r\n                    },\r\n                    {\r\n                        \"X\": 448,\r\n                        \"Y\": 232\r\n                    }\r\n                ],\r\n                \"AdvancedInfo\": \"{\\\"Parag\\\":{\\\"ParagNo\\\":1}}\"\r\n            },\r\n            {\r\n                \"DetectedText\": \"Raffaello\",\r\n                \"Confidence\": 99,\r\n                \"ItemPolygon\": {\r\n                    \"X\": 396,\r\n                    \"Y\": 304,\r\n                    \"Width\": 282,\r\n                    \"Height\": 68\r\n                },\r\n                \"Polygon\": [\r\n                    {\r\n                        \"X\": 370,\r\n                        \"Y\": 233\r\n                    },\r\n                    {\r\n                        \"X\": 649,\r\n                        \"Y\": 265\r\n                    },\r\n                    {\r\n                        \"X\": 642,\r\n                        \"Y\": 331\r\n                    },\r\n                    {\r\n                        \"X\": 362,\r\n                        \"Y\": 299\r\n                    }\r\n                ],\r\n                \"AdvancedInfo\": \"{\\\"Parag\\\":{\\\"ParagNo\\\":2}}\"\r\n            },\r\n            {\r\n                \"DetectedText\": \"费列罗臻点坊\",\r\n                \"Confidence\": 99,\r\n                \"ItemPolygon\": {\r\n                    \"X\": 437,\r\n                    \"Y\": 385,\r\n                    \"Width\": 188,\r\n                    \"Height\": 32\r\n                },\r\n                \"Polygon\": [\r\n                    {\r\n                        \"X\": 402,\r\n                        \"Y\": 318\r\n                    },\r\n                    {\r\n                        \"X\": 587,\r\n                        \"Y\": 339\r\n                    },\r\n                    {\r\n                        \"X\": 584,\r\n                        \"Y\": 370\r\n                    },\r\n                    {\r\n                        \"X\": 398,\r\n                        \"Y\": 349\r\n                    }\r\n                ],\r\n                \"AdvancedInfo\": \"{\\\"Parag\\\":{\\\"ParagNo\\\":3}}\"\r\n            },\r\n            {\r\n                \"DetectedText\": \"拉斐尔脆雪柔\",\r\n                \"Confidence\": 99,\r\n                \"ItemPolygon\": {\r\n                    \"X\": 427,\r\n                    \"Y\": 435,\r\n                    \"Width\": 207,\r\n                    \"Height\": 34\r\n                },\r\n                \"Polygon\": [\r\n                    {\r\n                        \"X\": 386,\r\n                        \"Y\": 366\r\n                    },\r\n                    {\r\n                        \"X\": 591,\r\n                        \"Y\": 390\r\n                    },\r\n                    {\r\n                        \"X\": 587,\r\n                        \"Y\": 423\r\n                    },\r\n                    {\r\n                        \"X\": 382,\r\n                        \"Y\": 399\r\n                    }\r\n                ],\r\n                \"AdvancedInfo\": \"{\\\"Parag\\\":{\\\"ParagNo\\\":3}}\"\r\n            }\r\n        ],\r\n        \"Language\": \"zh\",\r\n        \"Angel\": 6.5,\r\n        \"PdfPageSize\": 0,\r\n        \"RequestId\": \"03e66873-5209-4d26-abee-c4acd66fab91\"\r\n    }\r\n}",
        "title": "Recognizing general print ([debugging tool](https://console.cloud.tencent.com/api/explorer?Product=ocr&Action=GeneralBasicOCR))"
      }
    ],
    "HKIDCardOCR": [
      {
        "document": "",
        "input": "https://ocr.tencentcloudapi.com/?Action=HKIDCardOCR\n&ImageUrl=https://xx/a.jpg\n&DetectFake=true\n&ReturnHeadImage=false\n&<Common request parameters>",
        "output": "{\r\n    \"Response\": {\r\n        \"CnName\": \"申能\",\r\n        \"EnName\": \"SAN, Nan\",\r\n        \"TelexCode\": \"300000000000\",\r\n        \"Sex\": \"Female\",\r\n        \"Birthday\": \"01-01-2001\",\r\n        \"Permanent\": 1,\r\n        \"IdNum\": \"C000000(E)\",\r\n        \"Symbol\": \"***AZ\",\r\n        \"FirstIssueDate\": \"(09-99)\",\r\n        \"CurrentIssueDate\": \"23-09-10\",\r\n        \"FakeDetectResult\": 1,\r\n        \"WarningCode\": [ -9102, -9103 ],\r\n        \"HeadImage\": \"xx\", \r\n        \"RequestId\": \"fba1c9ad-aeb3-4418-9ecf-80ab1b5fc875\"\r\n    }\r\n}",
        "title": "Recognizing Hong Kong (China) identity card"
      }
    ],
    "MLIDCardOCR": [
      {
        "document": "",
        "input": "https://ocr.tencentcloudapi.com/?Action=MLIDCardOCR\n&ImageUrl=https://xx/a.jpg\n&<Common request parameters>",
        "output": "{\r\n    \"Response\": {\r\n        \"Name\": \"KAVIN ONG KHI MN\",\r\n        \"ID\": \"710716-08-6085\",\r\n        \"Address\": \"NO 11 PERSIARN PERAJRIT 4 TAMA PERAK 31400 IPOH ERAK\",\r\n        \"Sex\": \"LEAKI\",\r\n        \"Birthday\": \"\",\r\n        \"Warn\": [],\r\n        \"Image\": \"\",\r\n        \"AdvancedInfo\": \"{\\\"ID\\\":{\\\"Confidence\\\":\\\"1.0000\\\"},\\\"Name\\\":{\\\"Confidence\\\":\\\"0.9996\\\"},\\\"Address\\\":{\\\"Confidence\\\":\\\"0.9997\\\"},\\\"Sex\\\":{\\\"Confidence\\\":\\\"0.9999\\\"}}\",\r\n        \"Type\": \"MyKad\",\r\n        \"RequestId\": \"c969da05-54e3-4d0a-a55d-b3ef90d4ebf5\"\r\n    }\r\n}",
        "title": "Recognizing Malaysian identity card"
      }
    ],
    "MLIDPassportOCR": [
      {
        "document": "",
        "input": "https://ocr.tencentcloudapi.com/?Action=MLIDPassportOCR\n&ImageBase64=Base64 encoding\n&<Common request parameters>",
        "output": "{\r\n    \"Response\": {\r\n        \"ID\": \"E6918C\",\r\n        \"Name\": \"LIM HEG CHUN STEE\",\r\n        \"IssuingCountry\": \"SGP\",\r\n        \"Nationality\": \"SGP\",\r\n        \"DateOfBirth\": \"\",\r\n        \"Sex\": \"M\",\r\n        \"DateOfExpiration\": \"230414\",\r\n        \"Warn\": [],\r\n        \"Image\": \"\",\r\n        \"AdvancedInfo\": \"{\\\"IssuingCountry\\\":{\\\"Confidence\\\":\\\"0.9500\\\"},\\\"Name\\\":{\\\"Confidence\\\":\\\"0.9500\\\"},\\\"ID\\\":{\\\"Confidence\\\":\\\"0.9500\\\"},\\\"Nationality\\\":{\\\"Confidence\\\":\\\"0.9500\\\"},\\\"Sex\\\":{\\\"Confidence\\\":\\\"0.9500\\\"},\\\"DateOfExpiration\\\":{\\\"Confidence\\\":\\\"0.9500\\\"}}\",\r\n        \"RequestId\": \"0ee989d3-d064-45ec-bccb-63f5064247b4\"\r\n    }\r\n}",
        "title": "Recognizing passport issued in Hong Kong/Macao/Taiwan (China) or other countries/regions ([debugging tool](https://console.cloud.tencent.com/api/explorer?Product=ocr&Action=MLIDPassportOCR))"
      }
    ],
    "TableOCR": [
      {
        "document": "",
        "input": "https://ocr.tencentcloudapi.com/?Action=TableOCR\n&ImageUrl=http%3A%2F%2Fimg3.redocn.com%2Ftupian%2F20180301%2Fkongbaiqiuzhijianlibiaogesheji_9230633.jpg\n&<Common request parameters>",
        "output": "{\r\n    \"Response\": {\r\n        \"TextDetections\": [\r\n            {\r\n                \"ColTl\": -1,\r\n                \"RowTl\": -1,\r\n                \"ColBr\": -1,\r\n                \"RowBr\": -1,\r\n                \"Text\": \"Item number\",\r\n                \"Type\": \"header\",\r\n                \"Confidence\": 99,\r\n                \"Polygon\": [\r\n                    {\r\n                        \"X\": 3378,\r\n                        \"Y\": 363\r\n                    },\r\n                    {\r\n                        \"X\": 3383,\r\n                        \"Y\": 646\r\n                    },\r\n                    {\r\n                        \"X\": 3304,\r\n                        \"Y\": 648\r\n                    },\r\n                    {\r\n                        \"X\": 3299,\r\n                        \"Y\": 365\r\n                    }\r\n                ],\r\n                \"AdvancedInfo\": \"{}\"\r\n            },\r\n            {\r\n                \"ColTl\": -1,\r\n                \"RowTl\": -1,\r\n                \"ColBr\": -1,\r\n                \"RowBr\": -1,\r\n                \"Text\": \"Dish/:11181 1 19 Medical 101\",\r\n                \"Type\": \"header\",\r\n                \"Confidence\": 53,\r\n                \"Polygon\": [\r\n                    {\r\n                        \"X\": 3470,\r\n                        \"Y\": 1285\r\n                    },\r\n                    {\r\n                        \"X\": 3501,\r\n                        \"Y\": 3092\r\n                    },\r\n                    {\r\n                        \"X\": 3361,\r\n                        \"Y\": 3094\r\n                    },\r\n                    {\r\n                        \"X\": 3330,\r\n                        \"Y\": 1287\r\n                    }\r\n                ],\r\n                \"AdvancedInfo\": \"{}\"\r\n            },\r\n            {\r\n                \"ColTl\": -1,\r\n                \"RowTl\": -1,\r\n                \"ColBr\": -1,\r\n                \"RowBr\": -1,\r\n                \"Text\": \"Export declaration form\",\r\n                \"Type\": \"header\",\r\n                \"Confidence\": 99,\r\n                \"Polygon\": [\r\n                    {\r\n                        \"X\": 3201,\r\n                        \"Y\": 2046\r\n                    },\r\n                    {\r\n                        \"X\": 3211,\r\n                        \"Y\": 2618\r\n                    },\r\n                    {\r\n                        \"X\": 3169,\r\n                        \"Y\": 2618\r\n                    },\r\n                    {\r\n                        \"X\": 3159,\r\n                        \"Y\": 2046\r\n                    }\r\n                ],\r\n                \"AdvancedInfo\": \"{}\"\r\n            },\r\n            {\r\n                \"ColTl\": -1,\r\n                \"RowTl\": -1,\r\n                \"ColBr\": -1,\r\n                \"RowBr\": -1,\r\n                \"Text\": \"Production and sales company name (required)\",\r\n                \"Type\": \"header\",\r\n                \"Confidence\": 98,\r\n                \"Polygon\": [\r\n                    {\r\n                        \"X\": 2525,\r\n                        \"Y\": 184\r\n                    },\r\n                    {\r\n                        \"X\": 2532,\r\n                        \"Y\": 594\r\n                    },\r\n                    {\r\n                        \"X\": 2491,\r\n                        \"Y\": 595\r\n                    },\r\n                    {\r\n                        \"X\": 2484,\r\n                        \"Y\": 185\r\n                    }\r\n                ],\r\n                \"AdvancedInfo\": \"{}\"\r\n            }\r\n        ],\r\n        \"Data\": \"bWxQSwECFAAUAAAACAAAAAAAcxSJldcBAAD9BQAADQAAAAAAAAAAAAAAAACtLAAAeGwvc3R5bGVzLnhtbFBLAQIUABQAAAAIAAAAAAC8TIYcSAYAAP4kAAATAAAAAAAAAAAAAAAAAK8uAAB4bC90aGVtZS90aGVtZTEueG1sUEsBAhQAFAAAAAgAAAAAANG5P9oECwAAUU0AABgAAAAAAAAAAAAAAAAAKDUAAHhsL3dvcmtzaGVldHMvc2hlZXQyLnhtbFBLAQIUABQAAAAIAAAAAADjsY7PqAMAAE8PAAAYAAAAAAAAAAAAAAAAAGJAAAB4bC93b3Jrc2hlZXRzL3NoZWV0MS54bWxQSwUGAAAAAAwADAALAwAAQEQAAAAA\",\r\n        \"RequestId\": \"98f8fcbf-933a-4e95-ac48-6f1a9308fs53\"\r\n    }\r\n}",
        "title": "Recognizing form"
      }
    ]
  },
  "version": "1.0"
}