{
  "actions": {
    "DescribeRiskAssessment": {
      "document": "This API is used to query risk assessment results.",
      "input": "DescribeRiskAssessmentRequest",
      "name": "Queries risk assessment results",
      "output": "DescribeRiskAssessmentResponse",
      "status": "online"
    }
  },
  "metadata": {
    "apiVersion": "2020-11-03",
    "serviceNameCN": "全栈式风控引擎",
    "serviceShortName": "rce"
  },
  "objects": {
    "DescribeRiskAssessmentRequest": {
      "document": "DescribeRiskAssessment request structure.",
      "members": [
        {
          "disabled": false,
          "document": "Business parameters",
          "example": "无",
          "member": "InputBizCryptoData",
          "name": "BizCryptoData",
          "required": true,
          "type": "object"
        }
      ],
      "type": "object"
    },
    "DescribeRiskAssessmentResponse": {
      "document": "DescribeRiskAssessment response structure.",
      "members": [
        {
          "disabled": false,
          "document": "Business output parameters.",
          "example": "无",
          "member": "OutputRiskAssessment",
          "name": "Data",
          "output_required": true,
          "type": "object",
          "value_allowed_null": false
        },
        {
          "document": "The unique request ID, generated by the server, will be returned for every request (if the request fails to reach the server for other reasons, the request will not obtain a RequestId). RequestId is required for locating a problem.",
          "member": "string",
          "name": "RequestId",
          "type": "string"
        }
      ],
      "type": "object"
    },
    "InputBizCryptoData": {
      "document": "Query input parameters of risk assessment results",
      "members": [
        {
          "disabled": false,
          "document": "Whether to authorize.",
          "example": "1",
          "member": "string",
          "name": "IsAuthorized",
          "required": true,
          "type": "string"
        },
        {
          "disabled": false,
          "document": "Encryption type.",
          "example": "1",
          "member": "string",
          "name": "CryptoType",
          "required": true,
          "type": "string"
        },
        {
          "disabled": false,
          "document": "Encrypted content.",
          "example": "无",
          "member": "string",
          "name": "CryptoContent",
          "required": true,
          "type": "string"
        }
      ],
      "usage": "in"
    },
    "OutputRiskAssessment": {
      "document": "Query output parameters of risk assessment results.",
      "members": [
        {
          "disabled": false,
          "document": "Return code.\nNote: This field may return null, indicating that no valid value is found.",
          "example": "0",
          "member": "int64",
          "name": "Code",
          "output_required": true,
          "type": "int",
          "value_allowed_null": true
        },
        {
          "disabled": false,
          "document": "Returned information\n\nNote: This field may return null, indicating that no valid value is found.",
          "example": "无",
          "member": "string",
          "name": "Message",
          "output_required": true,
          "type": "string",
          "value_allowed_null": true
        },
        {
          "disabled": false,
          "document": "Business details.\nNote: This field may return null, indicating that no valid value is found.",
          "example": "无",
          "member": "OutputRiskAssessmentInfo",
          "name": "Value",
          "output_required": true,
          "type": "object",
          "value_allowed_null": true
        },
        {
          "disabled": false,
          "document": "Request ID.\nNote: This field may return null, indicating that no valid value is found.",
          "example": "无",
          "member": "string",
          "name": "UUid",
          "output_required": true,
          "type": "string",
          "value_allowed_null": true
        }
      ],
      "usage": "out"
    },
    "OutputRiskAssessmentExtraInfoPair": {
      "document": "Risk assessment extended attribute key-value pairs.",
      "members": [
        {
          "disabled": false,
          "document": "Key.\nNote: This field may return null, indicating that no valid value is found.",
          "example": "brand",
          "member": "string",
          "name": "Key",
          "required": true,
          "type": "string",
          "value_allowed_null": true
        },
        {
          "disabled": false,
          "document": "Value.\nNote: This field may return null, indicating that no valid value is found.",
          "example": "apple",
          "member": "string",
          "name": "Value",
          "required": true,
          "type": "string",
          "value_allowed_null": true
        }
      ],
      "usage": "out"
    },
    "OutputRiskAssessmentInfo": {
      "document": "Query output parameters of risk assessment results.",
      "members": [
        {
          "disabled": false,
          "document": "Risk value.\nNote: This field may return null, indicating that no valid value is found.",
          "example": "pass",
          "member": "string",
          "name": "RiskLevel",
          "output_required": true,
          "type": "string",
          "value_allowed_null": true
        },
        {
          "disabled": false,
          "document": "Risk type.\nNote: This field may return null, indicating that no valid value is found.",
          "example": "[101,201]",
          "member": "int64",
          "name": "RiskType",
          "output_required": true,
          "type": "list",
          "value_allowed_null": true
        },
        {
          "disabled": false,
          "document": "Device identification\n\nNote: This field may return null, indicating that no valid value is found.",
          "example": "F802B8142******C4E40844D",
          "member": "string",
          "name": "DeviceId",
          "output_required": true,
          "type": "string",
          "value_allowed_null": true
        },
        {
          "disabled": false,
          "document": "Extended attributes.\nNote: This field may return null, indicating that no valid value is found.",
          "example": "无",
          "member": "OutputRiskAssessmentExtraInfoPair",
          "name": "ExtraInfo",
          "output_required": true,
          "type": "list",
          "value_allowed_null": true
        },
        {
          "disabled": false,
          "document": "Token generation timestamp.\nNote: This field may return null, indicating that no valid value is found.",
          "example": "1647330450369",
          "member": "string",
          "name": "TokenTime",
          "output_required": true,
          "type": "string",
          "value_allowed_null": true
        }
      ],
      "usage": "out"
    }
  },
  "version": "1.0"
}